{"trial_id": "0007", "hyperparameters": {"space": [{"class_name": "Choice", "config": {"name": "activation", "default": "relu", "conditions": [], "values": ["relu", "tanh"], "ordered": false}}, {"class_name": "Int", "config": {"name": "layers", "default": null, "conditions": [], "min_value": 2, "max_value": 6, "step": 1, "sampling": "linear"}}, {"class_name": "Int", "config": {"name": "units_0", "default": null, "conditions": [], "min_value": 1, "max_value": 1000, "step": 1, "sampling": "linear"}}, {"class_name": "Int", "config": {"name": "units_1", "default": null, "conditions": [], "min_value": 1, "max_value": 1000, "step": 1, "sampling": "linear"}}, {"class_name": "Choice", "config": {"name": "learning_rate", "default": 0.01, "conditions": [], "values": [0.01, 0.001, 0.0001], "ordered": true}}, {"class_name": "Int", "config": {"name": "units_2", "default": null, "conditions": [], "min_value": 1, "max_value": 1000, "step": 1, "sampling": "linear"}}, {"class_name": "Int", "config": {"name": "units_3", "default": null, "conditions": [], "min_value": 1, "max_value": 1000, "step": 1, "sampling": "linear"}}, {"class_name": "Int", "config": {"name": "units_4", "default": null, "conditions": [], "min_value": 1, "max_value": 1000, "step": 1, "sampling": "linear"}}, {"class_name": "Int", "config": {"name": "units_5", "default": null, "conditions": [], "min_value": 1, "max_value": 1000, "step": 1, "sampling": "linear"}}], "values": {"activation": "tanh", "layers": 5, "units_0": 769, "units_1": 478, "learning_rate": 0.01, "units_2": 863, "units_3": 74, "units_4": 526, "units_5": 206, "tuner/epochs": 5, "tuner/initial_epoch": 0, "tuner/bracket": 0, "tuner/round": 0}}, "metrics": {"metrics": {"loss": {"direction": "min", "observations": [{"value": [2.387248992919922], "step": 4}]}, "accuracy": {"direction": "max", "observations": [{"value": [0.19046667218208313], "step": 4}]}, "val_loss": {"direction": "min", "observations": [{"value": [2.372959852218628], "step": 4}]}, "val_accuracy": {"direction": "max", "observations": [{"value": [0.195700004696846], "step": 4}]}}}, "score": 0.195700004696846, "best_step": 4, "status": "COMPLETED", "message": null}